freeassoc/__init__.py
freeassoc/analysis.py
freeassoc/cache.py
freeassoc/chat.py
freeassoc/clustering.py
freeassoc/core.py
freeassoc/embeddings.py
freeassoc/projection.py
freeassoc-0.1.0.dist-info/licenses/LICENSE
freeassoc-0.1.0.dist-info/METADATA
freeassoc-0.1.0.dist-info/WHEEL
freeassoc-0.1.0.dist-info/top_level.txt
freeassoc-0.1.0.dist-info/RECORD
