Metadata-Version: 2.4
Name: freeassoc
Version: 0.1.0
Summary: Lightweight utilities for free-association processing: cleaning, embedding, projection, clustering, and label inference.
Author-email: Ali Alhosseini <saaay71@gmail.com>
License-Expression: MIT
Project-URL: Homepage, https://example.com/freeassoc
Project-URL: Repository, https://example.com/freeassoc.git
Requires-Python: >=3.10
License-File: LICENSE
Requires-Dist: numpy
Requires-Dist: pandas
Requires-Dist: scipy
Requires-Dist: scikit-learn
Requires-Dist: tqdm
Dynamic: license-file
